setup.py
batchly_sdk/__init__.py
batchly_sdk/iprocessor.py
batchly_sdk.egg-info/PKG-INFO
batchly_sdk.egg-info/SOURCES.txt
batchly_sdk.egg-info/dependency_links.txt
batchly_sdk.egg-info/not-zip-safe
batchly_sdk.egg-info/top_level.txt
batchly_sdk/request/__init__.py
batchly_sdk/request/db_request.py
batchly_sdk/request/delimited_file_request.py
batchly_sdk/request/file_request.py
batchly_sdk/request/irequest.py
batchly_sdk/request/queue_request.py
batchly_sdk/response/__init__.py
batchly_sdk/response/db_response.py
batchly_sdk/response/default_response.py
batchly_sdk/response/file_response.py
batchly_sdk/response/iresponse.py