Metadata-Version: 1.0
Name: batchly_sdk
Version: 0.2.4
Summary: Service provider interface for the batchly processor system
Home-page: http://www.batchly.net
Author: Batchly Support
Author-email: support@batchly.net
License: Proprietary
Keywords: batchly processor sdk
Platform: UNKNOWN
